imgdb/__init__.py
imgdb/config.py
imgdb/exceptions.py
imgdb/image_processor.py
imgdb/imdb_data_handler.py
imgdb/imdb_poster_fetcher.py
imgdb/rt_parser.py
imgdb/utils.py
imgdb/resources/__init__.py
imgdb/resources/images/__init__.py
imgdb/resources/images/imdb_0.png
imgdb/resources/images/imdb_10.png
imgdb/resources/images/imdb_100.png
imgdb/resources/images/imdb_20.png
imgdb/resources/images/imdb_25.png
imgdb/resources/images/imdb_30.png
imgdb/resources/images/imdb_40.png
imgdb/resources/images/imdb_5.png
imgdb/resources/images/imdb_50.png
imgdb/resources/images/imdb_60.png
imgdb/resources/images/imdb_70.png
imgdb/resources/images/imdb_75.png
imgdb/resources/images/imdb_80.png
imgdb/resources/images/imdb_90.png
imgdb/resources/images/imdb_95.png
imgdb/resources/images/rt_0.png
imgdb/resources/images/rt_10.png
imgdb/resources/images/rt_100.png
imgdb/resources/images/rt_20.png
imgdb/resources/images/rt_25.png
imgdb/resources/images/rt_30.png
imgdb/resources/images/rt_40.png
imgdb/resources/images/rt_5.png
imgdb/resources/images/rt_50.png
imgdb/resources/images/rt_60.png
imgdb/resources/images/rt_70.png
imgdb/resources/images/rt_75.png
imgdb/resources/images/rt_80.png
imgdb/resources/images/rt_90.png
imgdb/resources/images/rt_95.png
imgdb-0.9.1.dist-info/LICENSE
imgdb-0.9.1.dist-info/METADATA
imgdb-0.9.1.dist-info/WHEEL
imgdb-0.9.1.dist-info/entry_points.txt
imgdb-0.9.1.dist-info/top_level.txt
imgdb-0.9.1.dist-info/RECORD
